rubrix/__init__.py
rubrix/__main__.py
rubrix/_version.py
rubrix-0.19.0.dist-info/LICENSE
rubrix-0.19.0.dist-info/METADATA
rubrix-0.19.0.dist-info/WHEEL
rubrix-0.19.0.dist-info/top_level.txt
rubrix-0.19.0.dist-info/RECORD
