Metadata-Version: 2.1
Name: rubrix
Version: 0.19.0
Summary: Open-source tool for exploring, labeling, and monitoring data for NLP projects.
Author-email: recognai <contact@recogn.ai>
Maintainer-email: recognai <contact@recogn.ai>
License: Apache-2.0
Project-URL: homepage, https://www.rubrix.ml
Project-URL: documentation, https://docs.rubrix.ml
Project-URL: repository, https://github.com/recognai/rubrix
Keywords: data-science,natural-language-processing,text-labeling,data-annotation,artificial-intelligence,knowledged-graph,developers-tools,human-in-the-loop,mlops
Requires-Python: >=3.7
License-File: LICENSE
Requires-Dist: argilla (~=1.0.0)
Provides-Extra: listeners
Provides-Extra: server
Requires-Dist: argilla[server] (~=1.0.0) ; extra == 'server'
